mslex/__init__.py
mslex/py.typed
mslex-1.1.0.dist-info/AUTHORS.rst
mslex-1.1.0.dist-info/LICENSE
mslex-1.1.0.dist-info/METADATA
mslex-1.1.0.dist-info/WHEEL
mslex-1.1.0.dist-info/entry_points.txt
mslex-1.1.0.dist-info/top_level.txt
mslex-1.1.0.dist-info/RECORD
