Metadata-Version: 2.1
Name: mslex
Version: 1.1.0
Summary: shlex for windows
Home-page: https://github.com/smoofra/mslex
Author: Lawrence D'Anna
Author-email: larry@elder-gods.org
License: Apache Software License 2.0
Keywords: mslex
Classifier: Development Status :: 5 - Production/Stable
Classifier: Intended Audience :: Developers
Classifier: License :: OSI Approved :: Apache Software License
Classifier: Natural Language :: English
Classifier: Programming Language :: Python :: 3
Classifier: Programming Language :: Python :: 3.5
Classifier: Programming Language :: Python :: 3.6
Classifier: Programming Language :: Python :: 3.7
Requires-Python: >=3.5
License-File: LICENSE
License-File: AUTHORS.rst
